bgpview/__init__.py
bgpview/api_client.py
bgpview/util.py
bgpview-0.1.0.dist-info/LICENSE
bgpview-0.1.0.dist-info/METADATA
bgpview-0.1.0.dist-info/WHEEL
bgpview-0.1.0.dist-info/top_level.txt
bgpview-0.1.0.dist-info/RECORD
